ytmusicapi/__init__.py
ytmusicapi/constants.py
ytmusicapi/continuations.py
ytmusicapi/enums.py
ytmusicapi/exceptions.py
ytmusicapi/helpers.py
ytmusicapi/navigation.py
ytmusicapi/setup.py
ytmusicapi/ytmusic.py
ytmusicapi/auth/__init__.py
ytmusicapi/auth/auth_parse.py
ytmusicapi/auth/browser.py
ytmusicapi/auth/types.py
ytmusicapi/auth/oauth/__init__.py
ytmusicapi/auth/oauth/credentials.py
ytmusicapi/auth/oauth/exceptions.py
ytmusicapi/auth/oauth/models.py
ytmusicapi/auth/oauth/token.py
ytmusicapi/locales/README.rst
ytmusicapi/locales/ar/LC_MESSAGES/base.mo
ytmusicapi/locales/de/LC_MESSAGES/base.mo
ytmusicapi/locales/en/LC_MESSAGES/base.mo
ytmusicapi/locales/es/LC_MESSAGES/base.mo
ytmusicapi/locales/fr/LC_MESSAGES/base.mo
ytmusicapi/locales/hi/LC_MESSAGES/base.mo
ytmusicapi/locales/it/LC_MESSAGES/base.mo
ytmusicapi/locales/ja/LC_MESSAGES/base.mo
ytmusicapi/locales/ko/LC_MESSAGES/base.mo
ytmusicapi/locales/nl/LC_MESSAGES/base.mo
ytmusicapi/locales/pt/LC_MESSAGES/base.mo
ytmusicapi/locales/ru/LC_MESSAGES/base.mo
ytmusicapi/locales/tr/LC_MESSAGES/base.mo
ytmusicapi/locales/ur/LC_MESSAGES/base.mo
ytmusicapi/locales/zh_CN/LC_MESSAGES/base.mo
ytmusicapi/locales/zh_TW/LC_MESSAGES/base.mo
ytmusicapi/mixins/__init__.py
ytmusicapi/mixins/_protocol.py
ytmusicapi/mixins/_utils.py
ytmusicapi/mixins/browsing.py
ytmusicapi/mixins/explore.py
ytmusicapi/mixins/library.py
ytmusicapi/mixins/playlists.py
ytmusicapi/mixins/podcasts.py
ytmusicapi/mixins/search.py
ytmusicapi/mixins/uploads.py
ytmusicapi/mixins/watch.py
ytmusicapi/models/__init__.py
ytmusicapi/models/lyrics.py
ytmusicapi/parsers/__init__.py
ytmusicapi/parsers/_utils.py
ytmusicapi/parsers/albums.py
ytmusicapi/parsers/browsing.py
ytmusicapi/parsers/explore.py
ytmusicapi/parsers/i18n.py
ytmusicapi/parsers/library.py
ytmusicapi/parsers/playlists.py
ytmusicapi/parsers/podcasts.py
ytmusicapi/parsers/search.py
ytmusicapi/parsers/songs.py
ytmusicapi/parsers/uploads.py
ytmusicapi/parsers/watch.py
ytmusicapi-1.10.0.dist-info/LICENSE
ytmusicapi-1.10.0.dist-info/METADATA
ytmusicapi-1.10.0.dist-info/WHEEL
ytmusicapi-1.10.0.dist-info/entry_points.txt
ytmusicapi-1.10.0.dist-info/top_level.txt
ytmusicapi-1.10.0.dist-info/RECORD
