Metadata-Version: 2.2
Name: ytmusicapi
Version: 1.10.0
Summary: Unofficial API for YouTube Music
Author-email: sigma67 <ytmusicapi@gmail.com>
License: MIT License
Project-URL: homepage, https://github.com/sigma67/ytmusicapi
Project-URL: documentation, https://ytmusicapi.readthedocs.io
Project-URL: repository, https://github.com/sigma67/ytmusicapi
Classifier: Programming Language :: Python :: 3
Classifier: License :: OSI Approved :: MIT License
Requires-Python: >=3.9
License-File: LICENSE
Requires-Dist: requests>=2.22
